maptial/__init__.py
maptial/geo/__init__.py
maptial/geo/geocalculator.py
maptial/geo/pdbcontacts.py
maptial/geo/pdbgeometry.py
maptial/geo/pdbloader.py
maptial/geo/pdbobject.py
maptial/geo/pdbspace.py
maptial/geo/reportmaker.py
maptial/map/__init__.py
maptial/map/atom.py
maptial/map/mapfunctions.py
maptial/map/maploader.py
maptial/map/mapobject.py
maptial/map/mapplothelp.py
maptial/map/mapplotter.py
maptial/map/mapsmanager.py
maptial/pol/__init__.py
maptial/pol/interpolator.py
maptial/pol/invariantmaker.py
maptial/pol/iteration.py
maptial/pol/iv1.py
maptial/pol/iv2.py
maptial/pol/iv3.py
maptial/pol/iv5.py
maptial/pol/scoring.py
maptial/xyz/__init__.py
maptial/xyz/axestransform.py
maptial/xyz/crstransform.py
maptial/xyz/gridmaker.py
maptial/xyz/matrix3d.py
maptial/xyz/matrixthree.py
maptial/xyz/matrixthreex.py
maptial/xyz/matrixthreey.py
maptial/xyz/spacetransform.py
maptial/xyz/vectorthree.py
maptial-0.0.14.dist-info/LICENSE
maptial-0.0.14.dist-info/METADATA
maptial-0.0.14.dist-info/WHEEL
maptial-0.0.14.dist-info/top_level.txt
maptial-0.0.14.dist-info/RECORD
